{
  "swagger": "2.0",
  "info": {
    "description": "Service manages students and teachers information",
    "version": "1.0",
    "title": "Service API"
  },
  "host": "localhost:8080",
  "basePath": "/",
  "tags": [
    {
      "name": "teacher-controller",
      "description": "Teacher Controller"
    },
    {
      "name": "student-controller",
      "description": "Student Controller"
    }
  ],
  "paths": {
    "/students": {
      "get": {
        "tags": [
          "student-controller"
        ],
        "summary": "Retrieving all the students",
        "operationId": "findAllStudentsUsingGET",
        "consumes": [
          "application/json"
        ],
        "produces": [
          "*/*"
        ],
        "responses": {
          "200": {
            "description": "Success",
            "schema": {
              "type": "array",
              "items": {
                "$ref": "#/definitions/StudentDTO"
              }
            }
          },
          "401": {
            "description": "Unauthorized"
          },
          "500": {
            "description": "Server error"
          },
          "403": {
            "description": "Forbidden"
          },
          "404": {
            "description": "Not Found"
          }
        }
      },
      "post": {
        "tags": [
          "student-controller"
        ],
        "summary": "Create Student",
        "operationId": "createStudentUsingPOST",
        "consumes": [
          "application/json"
        ],
        "produces": [
          "application/json"
        ],
        "parameters": [
          {
            "in": "body",
            "name": "studentDTO",
            "description": "studentDTO",
            "required": true,
            "schema": {
              "$ref": "#/definitions/StudentDTO"
            }
          }
        ],
        "responses": {
          "200": {
            "description": "OK",
            "schema": {
              "$ref": "#/definitions/StudentDTO"
            }
          },
          "201": {
            "description": "Created",
            "schema": {
              "$ref": "#/definitions/StudentDTO"
            }
          },
          "400": {
            "description": "Input message validation failed"
          },
          "401": {
            "description": "Unauthorized"
          },
          "500": {
            "description": "Server error"
          },
          "403": {
            "description": "Forbidden"
          },
          "404": {
            "description": "Not Found"
          }
        }
      }
    },
    "/teachers": {
      "get": {
        "tags": [
          "teacher-controller"
        ],
        "summary": "Retrieving all the teachers",
        "operationId": "findAllTeachersUsingGET",
        "consumes": [
          "application/json"
        ],
        "produces": [
          "*/*"
        ],
        "responses": {
          "200": {
            "description": "Success",
            "schema": {
              "type": "array",
              "items": {
                "$ref": "#/definitions/TeacherDTO"
              }
            }
          },
          "401": {
            "description": "Unauthorized"
          },
          "500": {
            "description": "Server error"
          },
          "403": {
            "description": "Forbidden"
          },
          "404": {
            "description": "Not Found"
          }
        }
      },
      "post": {
        "tags": [
          "teacher-controller"
        ],
        "summary": "Create Teacher",
        "operationId": "createTeacherUsingPOST",
        "consumes": [
          "application/json"
        ],
        "produces": [
          "application/json"
        ],
        "parameters": [
          {
            "in": "body",
            "name": "teacherDTO",
            "description": "teacherDTO",
            "required": true,
            "schema": {
              "$ref": "#/definitions/TeacherDTO"
            }
          }
        ],
        "responses": {
          "200": {
            "description": "OK",
            "schema": {
              "$ref": "#/definitions/TeacherDTO"
            }
          },
          "201": {
            "description": "Created",
            "schema": {
              "$ref": "#/definitions/TeacherDTO"
            }
          },
          "400": {
            "description": "Input message validation failed"
          },
          "401": {
            "description": "Unauthorized"
          },
          "500": {
            "description": "Server error"
          },
          "403": {
            "description": "Forbidden"
          },
          "404": {
            "description": "Not Found"
          }
        }
      }
    }
  },
  "definitions": {
    "TeacherDTO": {
      "type": "object",
      "properties": {
        "address": {
          "type": "string"
        },
        "id": {
          "type": "integer",
          "format": "int32"
        },
        "name": {
          "type": "string"
        }
      }
    },
    "StudentDTO": {
      "type": "object",
      "properties": {
        "address": {
          "type": "string"
        },
        "batch": {
          "type": "string"
        },
        "id": {
          "type": "integer",
          "format": "int32"
        },
        "name": {
          "type": "string"
        }
      }
    }
  }
}